Metadata-Version: 2.4
Name: calico-widget-docs
Version: 0.1.1
Summary: A Calico plugin to build widget documentation
Author: Emma Delescolle
License: MIT
Project-URL: Homepage, https://calico-ssg.com
Classifier: Framework :: Django :: 5
Classifier: License :: OSI Approved :: MIT License
Requires-Dist: calico_ssg
Requires-Dist: docstring_parser
